<?xml version="1.0" encoding="utf-8" ?>
<Defs>
	<ThingDef ParentName="ArtableFurnitureBase">
		<defName>ChangeMirror</defName>
		<label>change mirror</label>
		<description>Apply makeup and cut and dye hair.</description>
		<thingClass>ChangeMirror.Building_ChangeMirror</thingClass>
		<graphicData>
			<texPath>Furniture/ChangeMirror_mirror</texPath>
			<graphicClass>Graphic_Multi</graphicClass>
			<shaderType>CutoutComplex</shaderType>
			<drawSize>(1,1)</drawSize>
		</graphicData>
		<altitudeLayer>BuildingOnTop</altitudeLayer>
		<passability>Standable</passability>
		<fillPercent>0.4</fillPercent>
		<castEdgeShadows>false</castEdgeShadows>
		<stuffCategories>
			<li>Metallic</li>
			<li>Woody</li>
			<li>Stony</li>
		</stuffCategories>
		<costStuffCount>20</costStuffCount>
		<costList>
			<Steel>20</Steel>
		</costList>
		<defaultPlacingRot>South</defaultPlacingRot>
		<statBases>
			<MaxHitPoints>100</MaxHitPoints>
			<Mass>5</Mass>
			<WorkToBuild>1500</WorkToBuild>
			<Flammability>1.0</Flammability>
			<Beauty>5</Beauty>
		</statBases>
		<size>(1,1)</size>
		<designationHotKey>Misc12</designationHotKey>
		<staticSunShadowHeight>0.5</staticSunShadowHeight>
		<surfaceType>None</surfaceType>
		<canOverlapZones>false</canOverlapZones>
		<placeWorkers>
			<li>PlaceWorker_ShowFacilitiesConnections</li>
		</placeWorkers>
		<comps>
			<li Class="CompProperties_Facility">
				<statOffsets>
					<Comfort>0.05</Comfort>
				</statOffsets>
				<maxSimultaneous>1</maxSimultaneous>
				<maxDistance>8</maxDistance>
			</li>
		</comps>
		<building>
			<canPlaceOverWall>true</canPlaceOverWall>
			<isEdifice>false</isEdifice>
		</building>
		<hasInteractionCell>True</hasInteractionCell>
		<interactionCellOffset>(0,0,1)</interactionCellOffset>
		<designationCategory>Furniture</designationCategory>
	</ThingDef>
</Defs>